ngs_te_mapper2/__init__.py
ngs_te_mapper2/ngs_te_mapper2.py
ngs_te_mapper2/utility.py
ngs_te_mapper2-1.0.2.dist-info/LICENSE
ngs_te_mapper2-1.0.2.dist-info/METADATA
ngs_te_mapper2-1.0.2.dist-info/WHEEL
ngs_te_mapper2-1.0.2.dist-info/entry_points.txt
ngs_te_mapper2-1.0.2.dist-info/top_level.txt
ngs_te_mapper2-1.0.2.dist-info/RECORD
