Metadata-Version: 2.1
Name: ngs-te-mapper2
Version: 1.0.2
Summary: A program to identify transposable element insertions using next generation sequencing data
Home-page: https://github.com/bergmanlab/ngs_te_mapper2
Author: Shunhua Han
Author-email: hanshunhua0829@gmail.com
License: UNKNOWN
Platform: UNKNOWN
Classifier: Development Status :: 4 - Beta
Classifier: Programming Language :: Python :: 3.6
Classifier: Intended Audience :: Science/Research
Classifier: Topic :: Scientific/Engineering :: Bio-Informatics
Classifier: License :: OSI Approved :: BSD License
Requires-Python: >=3.6
License-File: LICENSE
